dynamodbPrettyParser/__init__.py
dynamodbPrettyParser/test.py
dynamodb_prettyparser-1.0.4.dist-info/LICENSE
dynamodb_prettyparser-1.0.4.dist-info/METADATA
dynamodb_prettyparser-1.0.4.dist-info/WHEEL
dynamodb_prettyparser-1.0.4.dist-info/top_level.txt
dynamodb_prettyparser-1.0.4.dist-info/RECORD
