Metadata-Version: 2.1
Name: dynamodb-prettyparser
Version: 1.0.4
Summary: Parses dynamodb responses into a list dictionaries with attribute names as keys
Home-page: https://github.com/QuiNovas/dynamodb-prettyparser
Author: Mathew Moon
Author-email: mmoon@quinovas.com
License: Apache 2.0
Platform: UNKNOWN
Classifier: Development Status :: 5 - Production/Stable
Classifier: Intended Audience :: Developers
Classifier: License :: OSI Approved :: Apache Software License
Classifier: Programming Language :: Python :: 3.7
